macroverse/__init__.py
macroverse/cli.py
macroverse/containers/base.py
macroverse/containers/docker.py
macroverse/containers/process.py
macroverse/hub.py
macroverse/main.py
macroverse/server.py
macroverse/ui/actions.py
macroverse/ui/environment/_name_/actions.py
macroverse/ui/environment/actions.py
macroverse/ui/html.py
macroverse/ui/layout.py
macroverse/ui/main.py
macroverse/ui/page.py
macroverse/ui/server/_id_/actions.py
macroverse/ui/server/_id_/environment/_name_/actions.py
macroverse/utils.py
macroverse-0.6.1.dist-info/WHEEL
macroverse-0.6.1.dist-info/entry_points.txt
macroverse-0.6.1.dist-info/METADATA
macroverse-0.6.1.dist-info/RECORD
