Metadata-Version: 2.3
Name: macroverse
Version: 0.6.1
Summary: Jupyverse environment deployment
Keywords: jupyter
Author: David Brochart
Author-email: David Brochart <david.brochart@gmail.com>
License: The MIT License (MIT)
Classifier: Development Status :: 4 - Beta
Classifier: Intended Audience :: Developers
Classifier: License :: OSI Approved :: MIT License
Classifier: Programming Language :: Python
Classifier: Programming Language :: Python :: 3.10
Classifier: Programming Language :: Python :: 3.11
Classifier: Programming Language :: Python :: 3.12
Classifier: Programming Language :: Python :: 3.13
Classifier: Programming Language :: Python :: 3.14
Classifier: Programming Language :: Python :: Implementation :: CPython
Requires-Dist: fps[fastapi,anycorn]>=0.5.8,<0.6.0
Requires-Dist: fps-auth
Requires-Dist: fps-login
Requires-Dist: fps-jupyterlab
Requires-Dist: fps-contents
Requires-Dist: fps-file-id
Requires-Dist: fps-file-watcher
Requires-Dist: fps-nbconvert
Requires-Dist: fps-yjs
Requires-Dist: fps-lab
Requires-Dist: fps-frontend
Requires-Dist: jupyverse-api
Requires-Dist: jupyter-collaboration-ui
Requires-Dist: jupyter-docprovider
Requires-Dist: cyclopts>=4.4.3,<5.0.0
Requires-Dist: holm>=0.8.1
Requires-Dist: pyyaml>=6.0.3,<7.0.0
Requires-Dist: httpx>=0.28.1,<1.0.0
Requires-Dist: structlog
Requires-Dist: psutil
Requires-Dist: types-psutil
Requires-Dist: types-pyyaml
Requires-Python: >=3.10
Project-URL: Homepage, https://github.com/davidbrochart/macroverse
